<?xml version = '1.0' encoding = 'UTF-8'?>
<Relation class="oracle.dbtools.crest.model.design.logical.Relation" name="Relation_47" directorySegmentName="seg_0" id="8A6A52AE-7EEB-012A-6ECB-C9092769F8AB">
<createdBy>laism</createdBy>
<createdTime>2023-06-02 02:07:54 UTC</createdTime>
<ownerDesignName>globaldatamodeler</ownerDesignName>
<engineerTo>
<item key="7AC3CF97-A9AF-C71B-8CC8-5C0C45F498F4" value="true"/>
</engineerTo>
<sourcePk>CA814471-5B59-99C8-A9D0-3DE7B4165473</sourcePk>
<identifying>false</identifying>
<optionalSource>true</optionalSource>
<optionalTarget>false</optionalTarget>
<sourceCardinality>1</sourceCardinality>
<sourceEntity>2A49FDDE-741D-F194-9B34-BF5126EF6357</sourceEntity>
<targetCardinalityString>1</targetCardinalityString>
<targetEntity>E5AD62FF-CCDC-1A04-1821-3D36A93AE877</targetEntity>
<transferable>true</transferable>
<deleteRule>NO ACTION</deleteRule>
</Relation>